Metadata-Version: 2.1
Name: sosq
Version: 1.0.5
Summary: Building Dataframe from Stack Overflow API with a search query and Saving data to csv file
Author-email: bakircius <burakbakirci@gmail.com>
Project-URL: Source, https://github.com/bakircius/sosq
Project-URL: Issues, https://github.com/bakircius/sosq/issues
Project-URL: Repository, https://github.com/bakircius/sosq.git
Classifier: Programming Language :: Python :: 3
Classifier: License :: OSI Approved :: MIT License
Classifier: Operating System :: OS Independent
Classifier: Development Status :: 5 - Production/Stable
Classifier: Framework :: IDLE
Classifier: Intended Audience :: Developers
Classifier: Natural Language :: English
Classifier: Programming Language :: Python :: 3
Classifier: Topic :: Scientific/Engineering :: Information Analysis
Requires-Python: >=3.8
License-File: LICENSE
Requires-Dist: requests
Requires-Dist: pandas
Requires-Dist: numpy
Requires-Dist: typing
